gsheetplot/Sheet_Plot.py
gsheetplot/__init__.py
gsheetplot-1.3.dist-info/METADATA
gsheetplot-1.3.dist-info/RECORD
gsheetplot-1.3.dist-info/WHEEL
gsheetplot-1.3.dist-info/top_level.txt
