Metadata-Version: 2.1
Name: gsheetplot
Version: 1.3
Summary: Helps in Visualising Google Sheet Data. To Use this package, you should contain Cred.json which you will get from Developers Console and from that assign permission in Google Sheet to the mail in Cred and when initializing the class pass cred.json as first parameter and key (that you got from google sheet) as second parameter to Sheet_Plot of gsheetplot
Home-page: https://github.com/ChaitanyaUndavalli/GSheetPlot
Author: Undavalli Lalkrishnachaitanya
Author-email: undavalli.14@gmail.com
License: MIT
Keywords: Python-Data-Visualization Bar-Graph Python-Package Google-Sheet-Visualisation Matplotlib
Platform: UNKNOWN
Classifier: Development Status :: 3 - Alpha
Classifier: License :: OSI Approved :: MIT License
Classifier: Programming Language :: Python :: 3.7
Requires-Dist: matplotlib
Requires-Dist: gspread
